gosh_cli/__init__.py
gosh_cli/main.py
gosh_cli/cli/__init__.py
gosh_cli/cli/debug.py
gosh_cli/cli/help.py
gosh_cli/cli/run.py
gosh_cli/core/__init__.py
gosh_cli/core/config.py
gosh_cli/core/module_loader.py
gosh_cli/core/nextflow.py
gosh_cli/core/nextflow_log.py
gosh_cli/core/outputs.py
gosh_cli/core/params_wizard.py
gosh_cli/core/resources.py
gosh_cli/core/samplesheet.py
gosh_cli/utils/__init__.py
gosh_cli/utils/ai_helper.py
gosh_cli/utils/datasets.py
gosh_cli/utils/email.py
gosh_cli/utils/help_context.txt
gosh_cli/utils/log_parser.py
gosh_cli/utils/validators.py
gosh_cli-0.3.2.dist-info/licenses/LICENSE
gosh_cli-0.3.2.dist-info/METADATA
gosh_cli-0.3.2.dist-info/WHEEL
gosh_cli-0.3.2.dist-info/entry_points.txt
gosh_cli-0.3.2.dist-info/top_level.txt
gosh_cli-0.3.2.dist-info/RECORD
