Metadata-Version: 2.4
Name: gosh-cli
Version: 0.3.2
Summary: gOSh - gOS sHell: A CLI tool for the nf-gOS pipeline
Author: Shihab Dider
Classifier: Programming Language :: Python :: 3
Classifier: License :: OSI Approved :: MIT License
Classifier: Operating System :: OS Independent
Requires-Python: >=3.6
License-File: LICENSE
Requires-Dist: Click
Requires-Dist: openai
Dynamic: author
Dynamic: classifier
Dynamic: description
Dynamic: description-content-type
Dynamic: license-file
Dynamic: requires-dist
Dynamic: requires-python
Dynamic: summary
